README.md
setup.py
prprpr.egg-info/PKG-INFO
prprpr.egg-info/SOURCES.txt
prprpr.egg-info/dependency_links.txt
prprpr.egg-info/top_level.txt
wu/__init__.py
wu/wy.py